<?xml version = '1.0' encoding = 'UTF-8'?>
<TableProxyOraclev12c class="oracle.dbtools.crest.model.design.storage.oracle.v12c.TableProxyOraclev12c" name="CUSTS" directorySegmentName="seg_0" id="1180550A-328D-7607-EE5A-80ECF8AA95F6">
<createdBy>User</createdBy>
<createdTime>2022-05-14 03:04:24 UTC</createdTime>
<ownerDesignName>데이터분석_loan</ownerDesignName>
<schemaObject>D66FAF66-ED1A-36D5-DB6E-92AEF7F4C550</schemaObject>
<logging>YES</logging>
<partitionedRowMovement>DISABLE</partitionedRowMovement>
<segment>8E4EDA38-01E0-4A0F-8995-F59F28BB4897</segment>
<tableSpace>9108F16A-0C25-7834-82E9-A8EE5EC96D69</tableSpace>
<temporaryChanged>false</temporaryChanged>
<accessDriverType>oracle_loader</accessDriverType>
<rejectLimit></rejectLimit>
<inMemory>NO</inMemory>
<columnProxies itemClass="oracle.dbtools.crest.model.design.storage.oracle.v12c.ColumnProxyOraclev12c">
<ColumnProxy name="PHONE" id="15B37C0E-B961-C92D-E942-C5ADD03C871F">
<createdBy>User</createdBy>
<createdTime>2022-05-14 03:04:24 UTC</createdTime>
<ownerDesignName>데이터분석_loan</ownerDesignName>
</ColumnProxy>
<ColumnProxy name="BIRTHDAY" id="26FC15C9-5FD2-4FA2-91BD-CE9919330D23">
<createdBy>User</createdBy>
<createdTime>2022-05-14 03:04:24 UTC</createdTime>
<ownerDesignName>데이터분석_loan</ownerDesignName>
</ColumnProxy>
<ColumnProxy name="CUST_ID" id="39078959-6D90-7ED4-6F2E-9FDE184DE00D">
<createdBy>User</createdBy>
<createdTime>2022-05-14 03:04:24 UTC</createdTime>
<ownerDesignName>데이터분석_loan</ownerDesignName>
</ColumnProxy>
<ColumnProxy name="ADDRESS" id="3EC9C895-172D-5090-7016-B07C73F15501">
<createdBy>User</createdBy>
<createdTime>2022-05-14 03:04:24 UTC</createdTime>
<ownerDesignName>데이터분석_loan</ownerDesignName>
</ColumnProxy>
<ColumnProxy name="FNAME" id="3F14C372-CDCD-F449-0BE5-6EC319BD6E48">
<createdBy>User</createdBy>
<createdTime>2022-05-14 03:04:24 UTC</createdTime>
<ownerDesignName>데이터분석_loan</ownerDesignName>
</ColumnProxy>
<ColumnProxy name="EMAIL" id="4DA3C4CF-C7EE-CCF7-5104-6BF715A959E6">
<createdBy>User</createdBy>
<createdTime>2022-05-14 03:04:24 UTC</createdTime>
<ownerDesignName>데이터분석_loan</ownerDesignName>
</ColumnProxy>
<ColumnProxy name="GENDER" id="773A8D17-E26D-5DA5-DB68-7D9712CE9DDA">
<createdBy>User</createdBy>
<createdTime>2022-05-14 03:04:24 UTC</createdTime>
<ownerDesignName>데이터분석_loan</ownerDesignName>
</ColumnProxy>
<ColumnProxy name="LNAME" id="8C6FA984-BD34-1D28-B3F6-B4D2D346D081">
<createdBy>User</createdBy>
<createdTime>2022-05-14 03:04:24 UTC</createdTime>
<ownerDesignName>데이터분석_loan</ownerDesignName>
</ColumnProxy>
<ColumnProxy name="CREDIT_LIMIT" id="AF596633-4C37-7C70-12B7-35A08E55180C">
<createdBy>User</createdBy>
<createdTime>2022-05-14 03:04:24 UTC</createdTime>
<ownerDesignName>데이터분석_loan</ownerDesignName>
</ColumnProxy>
<ColumnProxy name="CITY" id="CEB1E4E8-D0F8-5CFC-6DFC-D3703D593CF7">
<createdBy>User</createdBy>
<createdTime>2022-05-14 03:04:24 UTC</createdTime>
<ownerDesignName>데이터분석_loan</ownerDesignName>
</ColumnProxy>
<ColumnProxy name="COUNTRY" id="E0423267-9060-6846-3485-9211E74DD6A5">
<createdBy>User</createdBy>
<createdTime>2022-05-14 03:04:24 UTC</createdTime>
<ownerDesignName>데이터분석_loan</ownerDesignName>
</ColumnProxy>
</columnProxies>
<indexProxies>
<IndexProxy class="oracle.dbtools.crest.model.design.storage.oracle.v10g.IndexProxyOraclev10g" name="CUSTS_PK" id="531E8F64-3085-8C03-BD77-0C01DEC6E2DA">
<createdBy>User</createdBy>
<createdTime>2022-05-14 03:04:26 UTC</createdTime>
<ownerDesignName>데이터분석_loan</ownerDesignName>
<schemaObject>D66FAF66-ED1A-36D5-DB6E-92AEF7F4C550</schemaObject>
<segment>55B717C4-A033-A0C7-108B-00BC442E0DBF</segment>
<tableSpace>9108F16A-0C25-7834-82E9-A8EE5EC96D69</tableSpace>
</IndexProxy>
</indexProxies>
<primaryKeys>
<PrimaryKey class="oracle.dbtools.crest.model.design.storage.oracle.v10g.PKProxyOraclev10g" name="CUSTS_PK" id="A764B977-40DA-1E89-311C-B28B4B041465">
<createdBy>User</createdBy>
<createdTime>2022-05-14 03:04:29 UTC</createdTime>
<ownerDesignName>데이터분석_loan</ownerDesignName>
<segment>55B717C4-A033-A0C7-108B-00BC442E0DBF</segment>
<tableSpace>9108F16A-0C25-7834-82E9-A8EE5EC96D69</tableSpace>
<existingIndex>531E8F64-3085-8C03-BD77-0C01DEC6E2DA</existingIndex>
<indexSegment>55B717C4-A033-A0C7-108B-00BC442E0DBF</indexSegment>
<indexSort>SORTED</indexSort>
<usingIndex>BY INDEX NAME</usingIndex>
</PrimaryKey>
</primaryKeys>
</TableProxyOraclev12c>
